MANIFEST.in
README.md
setup.cfg
setup.py
versioneer.py
mantid_total_scattering.egg-info/PKG-INFO
mantid_total_scattering.egg-info/SOURCES.txt
mantid_total_scattering.egg-info/dependency_links.txt
mantid_total_scattering.egg-info/entry_points.txt
mantid_total_scattering.egg-info/requires.txt
mantid_total_scattering.egg-info/top_level.txt
tests/__init__.py
tests/file_handling/__init__.py
tests/file_handling/test_configure_geometry.py
tests/file_handling/test_load.py
tests/file_handling/test_save.py
tests/system/__init__.py
tests/system/polaris.py
tests/total_scattering/__init__.py
tests/total_scattering/test_utils.py
total_scattering/__init__.py
total_scattering/_version.py
total_scattering/cli.py
total_scattering/utils.py
total_scattering/file_handling/__init__.py
total_scattering/file_handling/load.py
total_scattering/file_handling/save.py
total_scattering/inelastic/__init__.py
total_scattering/inelastic/incident_spectrum.py
total_scattering/inelastic/placzek.py
total_scattering/isis/__init__.py
total_scattering/isis/polaris/__init__.py
total_scattering/isis/polaris/generate_input.py
total_scattering/reduction/__init__.py
total_scattering/reduction/total_scattering_reduction.py