Metadata-Version: 2.1
Name: mantid_total_scattering
Version: 0.2.10
Summary: Mantid Total Scattering Reduction
Home-page: https://github.com/marshallmcdonnell/mantid_total_scattering
Author: Marshall, Elliot, Pete
Author-email: mcondonnellmd@ornl.gov
License: GPL License (version 3)
Platform: UNKNOWN
